<odoo>
        <record id="group_etudiant" model="res.groups">
            <field name="name">etudiant</field>
        </record>
        <record id="group_respoDE" model="res.groups">
            <field name="name">respoDE</field>
        </record>
        <record id="group_enseignant" model="res.groups">
            <field name="name">enseignant</field>
        </record>
        <record model="ir.rule" id="vois_demandes">
        <field name="name">voir_ses_propres_demandes</field>
        <field name="model_id" ref="model_tutorat_demande"/>
         <field name="domain_force">[('user_id',=,user.id)]</field>
          <field name="groups" eval="[(4,ref('group_etudiant'))]"/>
             <field name="perm_read" eval="1"/>
           <field name="perm_write" eval="1"/>
   <field name="perm_create" eval="1"/>
   <field name="perm_unlink" eval="1"/>

    </record> 
</odoo>